ipc_option/__init__.py
ipc_option/option.py
ipc_option-0.0.8.dist-info/METADATA
ipc_option-0.0.8.dist-info/RECORD
ipc_option-0.0.8.dist-info/WHEEL
ipc_option-0.0.8.dist-info/top_level.txt
