Metadata-Version: 2.1
Name: ipc-option
Version: 0.0.8
Summary: option module for inner submodules
Home-page: https://blog.huangyu.me
Author: Yu Huang
Author-email: diwang90@qq.com
License: UNKNOWN
Platform: UNKNOWN
Classifier: Programming Language :: Python :: 3
Classifier: License :: OSI Approved :: MIT License
Classifier: Operating System :: OS Independent
